cnwi/__init__.py
cnwi/acas.py
cnwi/cmap.py
cnwi/datacube.py
cnwi/datasets.py
cnwi/derivatives.py
cnwi/elev.py
cnwi/fourier.py
cnwi/moa.py
cnwi/opt.py
cnwi/prebuilt.py
cnwi/rf.py
cnwi/sar.py
cnwi/sfilters.py
cnwi/stack.py
cnwi/trainingd.py
cnwi/data/__init__.py
cnwi/tools/__init__.py
cnwi/tools/prep_training_data.py
cnwi/tools/to_cloud/__init__.py
cnwi/tools/to_cloud/variables.py
cnwigee-1.0.1.dist-info/LICENSE
cnwigee-1.0.1.dist-info/METADATA
cnwigee-1.0.1.dist-info/WHEEL
cnwigee-1.0.1.dist-info/top_level.txt
cnwigee-1.0.1.dist-info/RECORD
