Metadata-Version: 2.1
Name: cnwigee
Version: 1.0.1
Summary: Your description of the project
Author: Ryan Hamilton
Author-email: ryangilberthamilton@gmail.com
Classifier: Programming Language :: Python :: 3
Classifier: Operating System :: OS Independent
License-File: LICENSE
